examplebtug6/__init__.py
examplebtug6/example.py
examplebtug6-0.0.1.dist-info/LICENSE.txt
examplebtug6-0.0.1.dist-info/METADATA
examplebtug6-0.0.1.dist-info/WHEEL
examplebtug6-0.0.1.dist-info/top_level.txt
examplebtug6-0.0.1.dist-info/RECORD
